{
  "annotations": {
    "changelogDate": "20231221191415"
  },
  "applications": "*",
  "entityTableName": "comment",
  "fields": [
    {
      "fieldName": "content",
      "fieldType": "String",
      "fieldValidateRules": ["required"]
    },
    {
      "fieldName": "commentDate",
      "fieldType": "Instant",
      "fieldValidateRules": ["required"]
    }
  ],
  "name": "Comment",
  "relationships": [
    {
      "otherEntityName": "incident",
      "otherEntityRelationshipName": "comment",
      "relationshipName": "incident",
      "relationshipSide": "right",
      "relationshipType": "many-to-one"
    }
  ],
  "searchEngine": "no"
}
